TP_Frida/__init__.py
TP_Frida-2024.7.7.dist-info/LICENSE
TP_Frida-2024.7.7.dist-info/METADATA
TP_Frida-2024.7.7.dist-info/WHEEL
TP_Frida-2024.7.7.dist-info/entry_points.txt
TP_Frida-2024.7.7.dist-info/top_level.txt
TP_Frida-2024.7.7.dist-info/RECORD
