Metadata-Version: 2.1
Name: TP-Frida
Version: 2024.7.7
Home-page: https://github.com/truocphan/TP-Frida
Author: TP Cyber Security
Author-email: tpcybersec2023@gmail.com
License: MIT
Classifier: Programming Language :: Python :: 3
Classifier: Programming Language :: Python :: 2
License-File: LICENSE
Requires-Dist: frida
Requires-Dist: typing-extensions
